nusselt/__init__.py
nusselt/__version__.py
nusselt/architectures/__init__.py
nusselt/architectures/ditn/__init__.py
nusselt/architectures/ditn/ditn_real.py
nusselt/architectures/omnisr/__init__.py
nusselt/architectures/omnisr/esa.py
nusselt/architectures/omnisr/layernorm.py
nusselt/architectures/omnisr/omnisr.py
nusselt/architectures/omnisr/osa.py
nusselt/architectures/omnisr/osag.py
nusselt/architectures/omnisr/pixelshuffle.py
nusselt/architectures/span/__init__.py
nusselt/architectures/span/span.py
nusselt/registry/__init__.py
nusselt/registry/architecture_registry.py
nusselt/registry/default_registry.py
nusselt/registry/model_descriptor.py
nusselt/transformers/__init__.py
nusselt/transformers/image_transformer.py
nusselt/transformers/model_loader.py
nusselt/utilities/__init__.py
nusselt/utilities/canonicalize.py
nusselt/utilities/state.py
nusselt/utilities/unpickler.py
nusselt-0.1.1.dist-info/LICENSE
nusselt-0.1.1.dist-info/METADATA
nusselt-0.1.1.dist-info/WHEEL
nusselt-0.1.1.dist-info/RECORD
