Metadata-Version: 2.1
Name: nusselt
Version: 0.1.1
Summary: Dependency for recognizing and executing Image Super-Resolution PyTorch architectures
Home-page: https://github.com/scanlate-wiki/nusselt
Author: Sekiju
Requires-Python: >=3.10,<4
Classifier: Programming Language :: Python :: 3
Classifier: Programming Language :: Python :: 3.10
Classifier: Programming Language :: Python :: 3.11
Classifier: Programming Language :: Python :: 3.12
Requires-Dist: einops (>=0.7.0,<0.8.0)
Requires-Dist: numpy (>=1.26.3,<2.0.0)
Requires-Dist: opencv-python (>=4.9.0.80,<5.0.0.0)
Requires-Dist: safetensors (>=0.4.2,<0.5.0)
Requires-Dist: torch (==2.1.2)
Requires-Dist: torchvision (==0.16.2)
